mannaggia_bot/__init__.py
mannaggia_bot/__main__.py
mannaggia_bot-0.1.1.dev20220824.dist-info/LICENSE
mannaggia_bot-0.1.1.dev20220824.dist-info/METADATA
mannaggia_bot-0.1.1.dev20220824.dist-info/WHEEL
mannaggia_bot-0.1.1.dev20220824.dist-info/entry_points.txt
mannaggia_bot-0.1.1.dev20220824.dist-info/top_level.txt
mannaggia_bot-0.1.1.dev20220824.dist-info/RECORD
