Metadata-Version: 2.1
Name: mannaggia-bot
Version: 0.1.1.dev20220824
Summary: mannaggia-bot is the official telegram bot for mannaggia
Home-page: https://github.com/veeso/mannaggia-bot
Author: Christian veeso Visintin
Author-email: christian.visintin1997@gmail.com
License: WTFPL
Keywords: mannaggia,debugging-tools,telegram,telegram-bot
Platform: UNKNOWN
Classifier: Development Status :: 5 - Production/Stable
Classifier: Intended Audience :: Developers
Classifier: Intended Audience :: End Users/Desktop
Classifier: Programming Language :: Python :: 3
Classifier: Operating System :: OS Independent
Classifier: Programming Language :: Python :: 3
Classifier: Programming Language :: Python :: 3.5
Requires-Python: >=3.5
Requires-Dist: mannaggia (>=0.1.4)
Requires-Dist: python-telegram-bot (>=13.13)
